swarmrob/__init__.py
swarmrob/daemon.py
swarmrob/master.py
swarmrob/requirements.txt
swarmrob/swarmrob.py
swarmrob/worker.py
swarmrob/dockerengine/__init__.py
swarmrob/dockerengine/docker_container_list.py
swarmrob/dockerengine/docker_interface.py
swarmrob/logger/__init__.py
swarmrob/logger/evaluation_logger.py
swarmrob/logger/local_logger.py
swarmrob/logger/remote_logger.py
swarmrob/logger/remote_logging_server.py
swarmrob/service_allocation/__init__.py
swarmrob/service_allocation/cost_calculation.py
swarmrob/service_allocation/ortools_interface.py
swarmrob/services/__init__.py
swarmrob/services/edf_parser.py
swarmrob/services/service.py
swarmrob/services/service_composition.py
swarmrob/swarmengine/__init__.py
swarmrob/swarmengine/mode.py
swarmrob/swarmengine/swarm.py
swarmrob/swarmengine/swarm_engine.py
swarmrob/swarmengine/swarm_engine_master.py
swarmrob/swarmengine/swarm_engine_worker.py
swarmrob/swarmengine/swarmrob_d.py
swarmrob/utils/__init__.py
swarmrob/utils/cmd_helper.py
swarmrob/utils/cmd_parser.py
swarmrob/utils/config.py
swarmrob/utils/errors.py
swarmrob/utils/network.py
swarmrob/utils/process_helper.py
swarmrob/utils/pyro_interface.py
swarmrob/utils/table_builder.py
tests/__init__.py
tests/test_cmd_daemon.py
tests/test_cmd_master.py
tests/test_cmd_swarmrob.py
tests/test_cmd_worker.py
tests/dockerengine/__init__.py
tests/dockerengine/test_docker_container_list.py
tests/dockerengine/test_docker_interface.py
tests/dummy_daemon/__init__.py
tests/dummy_daemon/setup.py
tests/dummy_daemon/daemon_dummy/__init__.py
tests/dummy_daemon/daemon_dummy/daemon_dummy.py
tests/dummy_daemon/daemon_dummy/master_dummy.py
tests/dummy_daemon/daemon_dummy/swarm_engine_dummy.py
tests/dummy_daemon/daemon_dummy/worker_dummy.py
tests/dummy_daemon/daemon_dummy/logger/__init__.py
tests/dummy_daemon/daemon_dummy/logger/local_logger.py
tests/dummy_daemon/daemon_dummy/utils/__init__.py
tests/dummy_daemon/daemon_dummy/utils/config.py
tests/dummy_daemon/daemon_dummy/utils/errors.py
Swarmrob-0.1.1.dist-info/METADATA
Swarmrob-0.1.1.dist-info/WHEEL
Swarmrob-0.1.1.dist-info/dependency_links.txt
Swarmrob-0.1.1.dist-info/entry_points.txt
Swarmrob-0.1.1.dist-info/top_level.txt
Swarmrob-0.1.1.dist-info/RECORD
