Metadata-Version: 2.1
Name: Swarmrob
Version: 0.1.1
Summary: An Orchestration Tool for Container-based Robot Applications
Home-page: https://github.com/aljoschap/swarmrob
Author: Aljoscha Poertner
Author-email: aljoscha.poertner@fh-bielefeld.de
License: GPL v3
Platform: UNKNOWN
Classifier: License :: OSI Approved :: GNU General Public License v3 (GPLv3)
Classifier: Programming Language :: Python :: 3
Classifier: Programming Language :: Python :: 3.5
